scmappy/__init__.py
scmappy/scmap.py
scmappy-0.2.dist-info/LICENSE
scmappy-0.2.dist-info/METADATA
scmappy-0.2.dist-info/WHEEL
scmappy-0.2.dist-info/top_level.txt
scmappy-0.2.dist-info/RECORD
