Metadata-Version: 2.1
Name: scmappy
Version: 0.2
Summary: Cell annotation function
Home-page: https://github.com/gatocor/scmappy
Author: Gabriel Torregrosa Cortes
Author-email: g.torregrosa@outlook.com
Classifier: Programming Language :: Python :: 3
Classifier: License :: OSI Approved :: MIT License
Classifier: Operating System :: OS Independent
Requires-Python: >=3.5
License-File: LICENSE
